{
"type": "FeatureCollection",
"name": "JH",
"crs": { "type": "name", "properties": { "name": "urn:ogc:def:crs:OGC:1.3:CRS84" } },
"features": [
{ "type": "Feature", "properties": { "Name": "JH 123 — Jugendherberge Hohenstaufen", "description": "<b>JH Nr:</b> 123<br><b>Name:</b> Jugendherberge Hohenstaufen<br><b>Ort:</b> Göppingen-Hohenstaufen<br><b>Adresse:</b> Schottengasse 41 73037 Göppingen-Hohenstaufen<br><b>Telefon:</b> +49 7165 438<br><b>Bundesland:</b> Baden-Württemberg", "tessellate": -1, "extrude": 0, "visibility": -1 }, "geometry": { "type": "Point", "coordinates": [ 9.7215843, 48.7463585 ] } }
]
}
