{
"type": "FeatureCollection",
"name": "JH",
"crs": { "type": "name", "properties": { "name": "urn:ogc:def:crs:OGC:1.3:CRS84" } },
"features": [
{ "type": "Feature", "properties": { "Name": "JH 199 — Jugendherberge Augsburg", "description": "<b>JH Nr:</b> 199<br><b>Name:</b> Jugendherberge Augsburg<br><b>Ort:</b> Augsburg<br><b>Adresse:</b> Unterer Graben 6 86152 Augsburg<br><b>Telefon:</b> +49 821 780889-0<br><b>Bundesland:</b> Bayern", "tessellate": -1, "extrude": 0, "visibility": -1 }, "geometry": { "type": "Point", "coordinates": [ 10.901942, 48.3728124 ] } }
]
}
