{
"type": "FeatureCollection",
"name": "JH",
"crs": { "type": "name", "properties": { "name": "urn:ogc:def:crs:OGC:1.3:CRS84" } },
"features": [
{ "type": "Feature", "properties": { "Name": "JH 117 — Geschwister-Scholl-Jugendherberge", "description": "<b>JH Nr:</b> 117<br><b>Name:</b> Geschwister-Scholl-Jugendherberge<br><b>Ort:</b> Ulm<br><b>Adresse:</b> Grimmelfinger Weg 45 89077 Ulm<br><b>Telefon:</b> +49 731 384455<br><b>Bundesland:</b> Baden-Württemberg", "tessellate": -1, "extrude": 0, "visibility": -1 }, "geometry": { "type": "Point", "coordinates": [ 9.9583782, 48.3803396 ] } }
]
}
