{
"type": "FeatureCollection",
"name": "JH",
"crs": { "type": "name", "properties": { "name": "urn:ogc:def:crs:OGC:1.3:CRS84" } },
"features": [
{ "type": "Feature", "properties": { "Name": "JH 16 — Helmut-Walser-Jugendherberge", "description": "<b>JH Nr:</b> 16<br><b>Name:</b> Helmut-Walser-Jugendherberge<br><b>Ort:</b> Lörrach<br><b>Adresse:</b> Steinenweg 40 79540 Lörrach<br><b>Telefon:</b> +49 7621 47040<br><b>Bundesland:</b> Baden-Württemberg", "tessellate": -1, "extrude": 0, "visibility": -1 }, "geometry": { "type": "Point", "coordinates": [ 7.6782153, 47.6004906 ] } }
]
}
