{
"type": "FeatureCollection",
"name": "JH",
"crs": { "type": "name", "properties": { "name": "urn:ogc:def:crs:OGC:1.3:CRS84" } },
"features": [
{ "type": "Feature", "properties": { "Name": "JH 10 — Jugendherberge Heidelberg International", "description": "<b>JH Nr:</b> 10<br><b>Name:</b> Jugendherberge Heidelberg International<br><b>Ort:</b> Heidelberg<br><b>Adresse:</b> Tiergartenstr. 5 69120 Heidelberg<br><b>Telefon:</b> +49 6221 651190<br><b>Bundesland:</b> Baden-Württemberg", "tessellate": -1, "extrude": 0, "visibility": -1 }, "geometry": { "type": "Point", "coordinates": [ 8.6593708, 49.4162168 ] } }
]
}
