{
"type": "FeatureCollection",
"name": "JH",
"crs": { "type": "name", "properties": { "name": "urn:ogc:def:crs:OGC:1.3:CRS84" } },
"features": [
{ "type": "Feature", "properties": { "Name": "JH 26 — Jugendherberge Menzenschwand", "description": "<b>JH Nr:</b> 26<br><b>Name:</b> Jugendherberge Menzenschwand<br><b>Ort:</b> St. Blasien-Menzenschwand<br><b>Adresse:</b> Vorderdorfstr. 10 79837 St. Blasien-Menzenschwand<br><b>Telefon:</b> +49 7675 326<br><b>Bundesland:</b> Baden-Württemberg", "tessellate": -1, "extrude": 0, "visibility": -1 }, "geometry": { "type": "Point", "coordinates": [ 8.0712724, 47.8152481 ] } }
]
}
