{
"type": "FeatureCollection",
"name": "JH",
"crs": { "type": "name", "properties": { "name": "urn:ogc:def:crs:OGC:1.3:CRS84" } },
"features": [
{ "type": "Feature", "properties": { "Name": "JH 239 — Jugendherberge Lenggries", "description": "<b>JH Nr:</b> 239<br><b>Name:</b> Jugendherberge Lenggries<br><b>Ort:</b> Lenggries<br><b>Adresse:</b> Jugendherbergstr. 10 83661 Lenggries<br><b>Telefon:</b> +49 8042 2424<br><b>Bundesland:</b> Bayern", "tessellate": -1, "extrude": 0, "visibility": -1 }, "geometry": { "type": "Point", "coordinates": [ 11.5752583, 47.6906258 ] } }
]
}
