{
"type": "FeatureCollection",
"name": "JH",
"crs": { "type": "name", "properties": { "name": "urn:ogc:def:crs:OGC:1.3:CRS84" } },
"features": [
{ "type": "Feature", "properties": { "Name": "JH 241 — Jugendherberge Lindau", "description": "<b>JH Nr:</b> 241<br><b>Name:</b> Jugendherberge Lindau<br><b>Ort:</b> Lindau<br><b>Adresse:</b> Herbergsweg 11 88131 Lindau<br><b>Telefon:</b> +49 8382 9671-0<br><b>Bundesland:</b> Bayern", "tessellate": -1, "extrude": 0, "visibility": -1 }, "geometry": { "type": "Point", "coordinates": [ 9.7002945, 47.5541817 ] } }
]
}
