{
"type": "FeatureCollection",
"name": "JH",
"crs": { "type": "name", "properties": { "name": "urn:ogc:def:crs:OGC:1.3:CRS84" } },
"features": [
{ "type": "Feature", "properties": { "Name": "JH 273 — Jugendherberge Burg Trausnitz", "description": "<b>JH Nr:</b> 273<br><b>Name:</b> Jugendherberge Burg Trausnitz<br><b>Ort:</b> Trausnitz<br><b>Adresse:</b> Burggasse 2 92555 Trausnitz<br><b>Telefon:</b> +49 9655 9215-0<br><b>Bundesland:</b> Bayern", "tessellate": -1, "extrude": 0, "visibility": -1 }, "geometry": { "type": "Point", "coordinates": [ 12.2640231, 49.5205259 ] } }
]
}
