{
"type": "FeatureCollection",
"name": "JH",
"crs": { "type": "name", "properties": { "name": "urn:ogc:def:crs:OGC:1.3:CRS84" } },
"features": [
{ "type": "Feature", "properties": { "Name": "JH 212 — Jugendherberge Dinkelsbühl", "description": "<b>JH Nr:</b> 212<br><b>Name:</b> Jugendherberge Dinkelsbühl<br><b>Ort:</b> Dinkelsbühl<br><b>Adresse:</b> Koppengasse 10 91550 Dinkelsbühl<br><b>Telefon:</b> +49 9851 5566-417<br><b>Bundesland:</b> Bayern", "tessellate": -1, "extrude": 0, "visibility": -1 }, "geometry": { "type": "Point", "coordinates": [ 10.3146621, 49.0693905 ] } }
]
}
