{
"type": "FeatureCollection",
"name": "JH",
"crs": { "type": "name", "properties": { "name": "urn:ogc:def:crs:OGC:1.3:CRS84" } },
"features": [
{ "type": "Feature", "properties": { "Name": "JH 268 — Jugendherberge Burg Wernfels", "description": "<b>JH Nr:</b> 268<br><b>Name:</b> Jugendherberge Burg Wernfels<br><b>Ort:</b> Spalt-Wernfels<br><b>Adresse:</b> Burgweg 7-9 91174 Spalt-Wernfels<br><b>Telefon:</b> +49 9873 976120<br><b>Bundesland:</b> Bayern", "tessellate": -1, "extrude": 0, "visibility": -1 }, "geometry": { "type": "Point", "coordinates": [ 10.8787899, 49.198018 ] } }
]
}
