{
"type": "FeatureCollection",
"name": "JH",
"crs": { "type": "name", "properties": { "name": "urn:ogc:def:crs:OGC:1.3:CRS84" } },
"features": [
{ "type": "Feature", "properties": { "Name": "JH 211 — Jugendherberge Dachau", "description": "<b>JH Nr:</b> 211<br><b>Name:</b> Jugendherberge Dachau<br><b>Ort:</b> Dachau<br><b>Adresse:</b> Roßwachtstr. 15 85221 Dachau<br><b>Telefon:</b> +49 8131 32295-0<br><b>Bundesland:</b> Bayern", "tessellate": -1, "extrude": 0, "visibility": -1 }, "geometry": { "type": "Point", "coordinates": [ 11.4515713, 48.2684285 ] } }
]
}
