{
"type": "FeatureCollection",
"name": "JH",
"crs": { "type": "name", "properties": { "name": "urn:ogc:def:crs:OGC:1.3:CRS84" } },
"features": [
{ "type": "Feature", "properties": { "Name": "JH 234 — Jugendherberge Kreuth", "description": "<b>JH Nr:</b> 234<br><b>Name:</b> Jugendherberge Kreuth<br><b>Ort:</b> Kreuth-Scharling<br><b>Adresse:</b> Nördliche Hauptstr. 91 83708 Kreuth-Scharling<br><b>Telefon:</b> +49 8029 9956-0<br><b>Bundesland:</b> Bayern", "tessellate": -1, "extrude": 0, "visibility": -1 }, "geometry": { "type": "Point", "coordinates": [ 11.7478541, 47.6643889 ] } }
]
}
