{
"type": "FeatureCollection",
"name": "JH",
"crs": { "type": "name", "properties": { "name": "urn:ogc:def:crs:OGC:1.3:CRS84" } },
"features": [
{ "type": "Feature", "properties": { "Name": "JH 339 — Jugendherberge Hagen", "description": "<b>JH Nr:</b> 339<br><b>Name:</b> Jugendherberge Hagen<br><b>Ort:</b> Hagen<br><b>Adresse:</b> Eppenhauser Str. 65 58093 Hagen<br><b>Telefon:</b> +49 2331 72849<br><b>Bundesland:</b> Nordrhein-Westfalen", "tessellate": -1, "extrude": 0, "visibility": -1 }, "geometry": { "type": "Point", "coordinates": [ 7.4984186, 51.3620979 ] } }
]
}
