{
"type": "FeatureCollection",
"name": "JH",
"crs": { "type": "name", "properties": { "name": "urn:ogc:def:crs:OGC:1.3:CRS84" } },
"features": [
{ "type": "Feature", "properties": { "Name": "JH 300 — Jugendherberge Hann. Münden", "description": "<b>JH Nr:</b> 300<br><b>Name:</b> Jugendherberge Hann. Münden<br><b>Ort:</b> Hann. Münden<br><b>Adresse:</b> Prof.-Oelkers-Str. 10 34346 Hann. Münden<br><b>Telefon:</b> +49 5541 8853<br><b>Bundesland:</b> Niedersachsen", "tessellate": -1, "extrude": 0, "visibility": -1 }, "geometry": { "type": "Point", "coordinates": [ 9.6368905, 51.4294516 ] } }
]
}
