{
"type": "FeatureCollection",
"name": "JH",
"crs": { "type": "name", "properties": { "name": "urn:ogc:def:crs:OGC:1.3:CRS84" } },
"features": [
{ "type": "Feature", "properties": { "Name": "JH 451 — City-Hostel", "description": "<b>JH Nr:</b> 451<br><b>Name:</b> City-Hostel<br><b>Ort:</b> Köln-Riehl<br><b>Adresse:</b> An der Schanz 14 50735 Köln-Riehl<br><b>Telefon:</b> +49 221 976513-0<br><b>Bundesland:</b> Nordrhein-Westfalen", "tessellate": -1, "extrude": 0, "visibility": -1 }, "geometry": { "type": "Point", "coordinates": [ 6.9856634, 50.9632111 ] } }
]
}
