{
"type": "FeatureCollection",
"name": "JH",
"crs": { "type": "name", "properties": { "name": "urn:ogc:def:crs:OGC:1.3:CRS84" } },
"features": [
{ "type": "Feature", "properties": { "Name": "JH 402 — Eifelmaar-Jugendherberge", "description": "<b>JH Nr:</b> 402<br><b>Name:</b> Eifelmaar-Jugendherberge<br><b>Ort:</b> Daun<br><b>Adresse:</b> Maria-Hilf-Straße 21 54550 Daun<br><b>Telefon:</b> +49 6592 2884<br><b>Bundesland:</b> Rheinland-Pfalz", "tessellate": -1, "extrude": 0, "visibility": -1 }, "geometry": { "type": "Point", "coordinates": [ 6.8346274, 50.1859877 ] } }
]
}
