{
"type": "FeatureCollection",
"name": "JH",
"crs": { "type": "name", "properties": { "name": "urn:ogc:def:crs:OGC:1.3:CRS84" } },
"features": [
{ "type": "Feature", "properties": { "Name": "JH 467 — Wellness-Jugendherberge", "description": "<b>JH Nr:</b> 467<br><b>Name:</b> Wellness-Jugendherberge<br><b>Ort:</b> Wiehl<br><b>Adresse:</b> An der Krähenhardt 6 51674 Wiehl<br><b>Telefon:</b> +49 2262 72777-0<br><b>Bundesland:</b> Nordrhein-Westfalen", "tessellate": -1, "extrude": 0, "visibility": -1 }, "geometry": { "type": "Point", "coordinates": [ 7.5541047, 50.9445954 ] } }
]
}
