{
"type": "FeatureCollection",
"name": "JH",
"crs": { "type": "name", "properties": { "name": "urn:ogc:def:crs:OGC:1.3:CRS84" } },
"features": [
{ "type": "Feature", "properties": { "Name": "JH 449 — St. Annaberg", "description": "<b>JH Nr:</b> 449<br><b>Name:</b> St. Annaberg<br><b>Ort:</b> Kleve<br><b>Adresse:</b> St. Annaberg 2 47533 Kleve<br><b>Telefon:</b> +49 2821 891450<br><b>Bundesland:</b> Nordrhein-Westfalen", "tessellate": -1, "extrude": 0, "visibility": -1 }, "geometry": { "type": "Point", "coordinates": [ 6.1065193, 51.7832425 ] } }
]
}
