{
"type": "FeatureCollection",
"name": "JH",
"crs": { "type": "name", "properties": { "name": "urn:ogc:def:crs:OGC:1.3:CRS84" } },
"features": [
{ "type": "Feature", "properties": { "Name": "JH 478 — Jugendherberge Eschwege", "description": "<b>JH Nr:</b> 478<br><b>Name:</b> Jugendherberge Eschwege<br><b>Ort:</b> Eschwege<br><b>Adresse:</b> Jardin-de-Saint-Mandé 1 37269 Eschwege<br><b>Telefon:</b> +49 5651 60099<br><b>Bundesland:</b> Hessen", "tessellate": -1, "extrude": 0, "visibility": -1 }, "geometry": { "type": "Point", "coordinates": [ 10.0655615, 51.1880843 ] } }
]
}
