{
"type": "FeatureCollection",
"name": "JH",
"crs": { "type": "name", "properties": { "name": "urn:ogc:def:crs:OGC:1.3:CRS84" } },
"features": [
{ "type": "Feature", "properties": { "Name": "JH 429 — Mosel-Jugendherberge", "description": "<b>JH Nr:</b> 429<br><b>Name:</b> Mosel-Jugendherberge<br><b>Ort:</b> Traben-Trarbach<br><b>Adresse:</b> Hirtenpfad 6 56841 Traben-Trarbach<br><b>Telefon:</b> +49 6541 9278<br><b>Bundesland:</b> Rheinland-Pfalz", "tessellate": -1, "extrude": 0, "visibility": -1 }, "geometry": { "type": "Point", "coordinates": [ 7.1274241, 49.9592986 ] } }
]
}
