{
"type": "FeatureCollection",
"name": "JH",
"crs": { "type": "name", "properties": { "name": "urn:ogc:def:crs:OGC:1.3:CRS84" } },
"features": [
{ "type": "Feature", "properties": { "Name": "JH 557 — Jugendherberge Wyk", "description": "<b>JH Nr:</b> 557<br><b>Name:</b> Jugendherberge Wyk<br><b>Ort:</b> Wyk auf Föhr<br><b>Adresse:</b> Fehrstieg 41 25938 Wyk auf Föhr<br><b>Telefon:</b> +49 4681 2355<br>", "tessellate": -1, "extrude": 0, "visibility": -1 }, "geometry": { "type": "Point", "coordinates": [ 8.5405524, 54.68431 ] } }
]
}
