{
"type": "FeatureCollection",
"name": "JH",
"crs": { "type": "name", "properties": { "name": "urn:ogc:def:crs:OGC:1.3:CRS84" } },
"features": [
{ "type": "Feature", "properties": { "Name": "JH 537 — Jugendherberge Bad Malente", "description": "<b>JH Nr:</b> 537<br><b>Name:</b> Jugendherberge Bad Malente<br><b>Ort:</b> Bad Malente<br><b>Adresse:</b> Kellerseestr. 48 23714 Bad Malente<br><b>Telefon:</b> +49 4523 1723<br><b>Bundesland:</b> Schleswig-Holstein", "tessellate": -1, "extrude": 0, "visibility": -1 }, "geometry": { "type": "Point", "coordinates": [ 10.5761927, 54.1743856 ] } }
]
}
