{
"type": "FeatureCollection",
"name": "JH",
"crs": { "type": "name", "properties": { "name": "urn:ogc:def:crs:OGC:1.3:CRS84" } },
"features": [
{ "type": "Feature", "properties": { "Name": "JH 556 — Jugendherberge Wittdün", "description": "<b>JH Nr:</b> 556<br><b>Name:</b> Jugendherberge Wittdün<br><b>Ort:</b> Wittdün auf Amrum<br><b>Adresse:</b> Mittelstr. 1 25946 Wittdün auf Amrum<br><b>Telefon:</b> +49 4682 2010<br>", "tessellate": -1, "extrude": 0, "visibility": -1 }, "geometry": { "type": "Point", "coordinates": [ 8.3949228, 54.6257344 ] } }
]
}
