{
"type": "FeatureCollection",
"name": "JH",
"crs": { "type": "name", "properties": { "name": "urn:ogc:def:crs:OGC:1.3:CRS84" } },
"features": [
{ "type": "Feature", "properties": { "Name": "JH 554 — Jugendherberge Westensee", "description": "<b>JH Nr:</b> 554<br><b>Name:</b> Jugendherberge Westensee<br><b>Ort:</b> Westensee<br><b>Adresse:</b> Am See 24 24259 Westensee<br><b>Telefon:</b> +49 4305 542<br><b>Bundesland:</b> Schleswig-Holstein", "tessellate": -1, "extrude": 0, "visibility": -1 }, "geometry": { "type": "Point", "coordinates": [ 9.9083144, 54.2746896 ] } }
]
}
