{
"type": "FeatureCollection",
"name": "JH",
"crs": { "type": "name", "properties": { "name": "urn:ogc:def:crs:OGC:1.3:CRS84" } },
"features": [
{ "type": "Feature", "properties": { "Name": "JH 588 — Jugendherberge Norderney", "description": "<b>JH Nr:</b> 588<br><b>Name:</b> Jugendherberge Norderney<br><b>Ort:</b> Norderney Dünensender<br><b>Adresse:</b> Am Dünensender 3 26548 Norderney Dünensender<br><b>Telefon:</b> +49 4932 2574<br><b>Bundesland:</b> Niedersachsen", "tessellate": -1, "extrude": 0, "visibility": -1 }, "geometry": { "type": "Point", "coordinates": [ 7.2058395, 53.7119115 ] } }
]
}
