{
"type": "FeatureCollection",
"name": "JH",
"crs": { "type": "name", "properties": { "name": "urn:ogc:def:crs:OGC:1.3:CRS84" } },
"features": [
{ "type": "Feature", "properties": { "Name": "JH 668 — Jugendherberge Xanten", "description": "<b>JH Nr:</b> 668<br><b>Name:</b> Jugendherberge Xanten<br><b>Ort:</b> Xanten<br><b>Adresse:</b> Bankscher Weg 4 46509 Xanten<br><b>Telefon:</b> +49 2801 9850-0<br><b>Bundesland:</b> Nordrhein-Westfalen", "tessellate": -1, "extrude": 0, "visibility": -1 }, "geometry": { "type": "Point", "coordinates": [ 6.4407018, 51.680414 ] } }
]
}
