{
"type": "FeatureCollection",
"name": "JH",
"crs": { "type": "name", "properties": { "name": "urn:ogc:def:crs:OGC:1.3:CRS84" } },
"features": [
{ "type": "Feature", "properties": { "Name": "JH 632 — Jugendherberge Greifswald", "description": "<b>JH Nr:</b> 632<br><b>Name:</b> Jugendherberge Greifswald<br><b>Ort:</b> Greifswald<br><b>Adresse:</b> Pestalozzistr. 11/12 17489 Greifswald<br><b>Telefon:</b> +49 3834 51690<br><b>Bundesland:</b> Mecklenburg-Vorpommern", "tessellate": -1, "extrude": 0, "visibility": -1 }, "geometry": { "type": "Point", "coordinates": [ 13.3835802, 54.0868005 ] } }
]
}
