{
"type": "FeatureCollection",
"name": "JH",
"crs": { "type": "name", "properties": { "name": "urn:ogc:def:crs:OGC:1.3:CRS84" } },
"features": [
{ "type": "Feature", "properties": { "Name": "JH 629 — Jugendherberge Wernigerode", "description": "<b>JH Nr:</b> 629<br><b>Name:</b> Jugendherberge Wernigerode<br><b>Ort:</b> Wernigerode<br><b>Adresse:</b> Am Eichberg 5 38855 Wernigerode<br><b>Telefon:</b> +49 3943 606176<br><b>Bundesland:</b> Sachsen-Anhalt", "tessellate": -1, "extrude": 0, "visibility": -1 }, "geometry": { "type": "Point", "coordinates": [ 10.7541026, 51.8262127 ] } }
]
}
