{
"type": "FeatureCollection",
"name": "JH",
"crs": { "type": "name", "properties": { "name": "urn:ogc:def:crs:OGC:1.3:CRS84" } },
"features": [
{ "type": "Feature", "properties": { "Name": "JH 618 — Jugendherberge Prebelow", "description": "<b>JH Nr:</b> 618<br><b>Name:</b> Jugendherberge Prebelow<br><b>Ort:</b> Prebelow<br><b>Adresse:</b> Prebelow 2 16831 Prebelow<br><b>Telefon:</b> +49 33921 70222<br><b>Bundesland:</b> Brandenburg", "tessellate": -1, "extrude": 0, "visibility": -1 }, "geometry": { "type": "Point", "coordinates": [ 12.8869406, 53.1756912 ] } }
]
}
