{
"type": "FeatureCollection",
"name": "JH",
"crs": { "type": "name", "properties": { "name": "urn:ogc:def:crs:OGC:1.3:CRS84" } },
"features": [
{ "type": "Feature", "properties": { "Name": "JH 63 — Jugendherberge Johanngeorgenstadt", "description": "<b>JH Nr:</b> 63<br><b>Name:</b> Jugendherberge Johanngeorgenstadt<br><b>Ort:</b> Johanngeorgenstadt<br><b>Adresse:</b> Hospitalstr. 5 08349 Johanngeorgenstadt<br><b>Telefon:</b> +49 3773 882194<br>", "tessellate": -1, "extrude": 0, "visibility": -1 }, "geometry": { "type": "Point", "coordinates": [ 12.7273908, 50.4228998 ] } }
]
}
