{
"type": "FeatureCollection",
"name": "JH",
"crs": { "type": "name", "properties": { "name": "urn:ogc:def:crs:OGC:1.3:CRS84" } },
"features": [
{ "type": "Feature", "properties": { "Name": "JH 82 — Jugendherberge Strehla", "description": "<b>JH Nr:</b> 82<br><b>Name:</b> Jugendherberge Strehla<br><b>Ort:</b> Strehla<br><b>Adresse:</b> Torgauer Str. 33 01616 Strehla<br><b>Telefon:</b> +49 35264 90330<br><b>Bundesland:</b> Sachsen", "tessellate": -1, "extrude": 0, "visibility": -1 }, "geometry": { "type": "Point", "coordinates": [ 13.2226093, 51.3590267 ] } }
]
}
