{
"type": "FeatureCollection",
"name": "JH",
"crs": { "type": "name", "properties": { "name": "urn:ogc:def:crs:OGC:1.3:CRS84" } },
"features": [
{ "type": "Feature", "properties": { "Name": "JH 93 — Jugendherberge Warmbad", "description": "<b>JH Nr:</b> 93<br><b>Name:</b> Jugendherberge Warmbad<br><b>Ort:</b> Warmbad<br><b>Adresse:</b> An der Jugendherberge 6 09429 Warmbad<br><b>Telefon:</b> +49 37369 9477<br><b>Bundesland:</b> Sachsen", "tessellate": -1, "extrude": 0, "visibility": -1 }, "geometry": { "type": "Point", "coordinates": [ 13.0832406, 50.6706797 ] } }
]
}
